fastapi_skywalking_trace/__init__.py
fastapi_skywalking_trace/middleware.py
fastapi_skywalking_trace-0.0.1.dist-info/LICENSE
fastapi_skywalking_trace-0.0.1.dist-info/METADATA
fastapi_skywalking_trace-0.0.1.dist-info/WHEEL
fastapi_skywalking_trace-0.0.1.dist-info/top_level.txt
fastapi_skywalking_trace-0.0.1.dist-info/RECORD
