Metadata-Version: 2.1
Name: fastapi-skywalking-trace
Version: 0.0.1
Summary: Fastapi Middleware to work with skywalking
Home-page: UNKNOWN
Author: SantoLabs
Author-email: santolabs@santodigital.com.br
License: UNKNOWN
Platform: UNKNOWN
Classifier: Programming Language :: Python :: 3
Classifier: License :: OSI Approved :: MIT License
Classifier: Operating System :: OS Independent
Requires-Python: >=3.6
License-File: LICENSE
Requires-Dist: starlette
Requires-Dist: apache-skywalking[http]
